README.md
setup.py
ERA_V2_Architecture/__init__.py
ERA_V2_Architecture.egg-info/PKG-INFO
ERA_V2_Architecture.egg-info/SOURCES.txt
ERA_V2_Architecture.egg-info/dependency_links.txt
ERA_V2_Architecture.egg-info/top_level.txt
ERA_V2_Architecture/model/CIFAR10Albumentations.py
ERA_V2_Architecture/model/__init__.py
ERA_V2_Architecture/model/gradCAM.py
ERA_V2_Architecture/model/models.py
ERA_V2_Architecture/model/resnet.py
ERA_V2_Architecture/model/util.py